rstms_bcc/__init__.py
rstms_bcc/app.py
rstms_bcc/browser.py
rstms_bcc/cli.py
rstms_bcc/client.py
rstms_bcc/exception_handler.py
rstms_bcc/models.py
rstms_bcc/passwd.py
rstms_bcc/settings.py
rstms_bcc/shell.py
rstms_bcc/version.py
rstms_bcc-2.1.8.dist-info/entry_points.txt
rstms_bcc-2.1.8.dist-info/licenses/LICENSE
rstms_bcc-2.1.8.dist-info/WHEEL
rstms_bcc-2.1.8.dist-info/METADATA
rstms_bcc-2.1.8.dist-info/RECORD
