Metadata-Version: 2.4
Name: rstms-bcc
Version: 2.1.8
Summary: Top-level package for bcc.
Keywords: baikal admin cli
Author-email: Matt Krueger <mkrueger@rstms.net>
Classifier: Intended Audience :: Developers
Classifier: Natural Language :: English
Classifier: Programming Language :: Python :: 3
Classifier: Programming Language :: Python :: 3.10
License-File: LICENSE
Requires-Dist: arrow==1.4.0
Requires-Dist: beautifulsoup4==4.14.3
Requires-Dist: click==8.2.0
Requires-Dist: pyyaml==6.0.2
Requires-Dist: requests==2.32.5
Requires-Dist: httpx==0.28.1
Requires-Dist: pydantic-core==2.33.1
Requires-Dist: pydantic==2.11.3
Requires-Dist: fastapi==0.128.0
Requires-Dist: uvicorn==0.40.0
Requires-Dist: cryptography==46.0.2
Requires-Dist: black ; extra == "dev"
Requires-Dist: bump2version ; extra == "dev"
Requires-Dist: coverage ; extra == "dev"
Requires-Dist: devtools ; extra == "dev"
Requires-Dist: flit ; extra == "dev"
Requires-Dist: flake8 ; extra == "dev"
Requires-Dist: flake8-length ; extra == "dev"
Requires-Dist: isort ; extra == "dev"
Requires-Dist: pdbpp ; extra == "dev"
Requires-Dist: pytest ; extra == "dev"
Requires-Dist: pytest-datadir ; extra == "dev"
Requires-Dist: pytest-asyncio ; extra == "dev"
Requires-Dist: psutil ; extra == "dev"
Requires-Dist: python-box ; extra == "dev"
Requires-Dist: psutil ; extra == "dev"
Requires-Dist: toml ; extra == "dev"
Requires-Dist: m2r2 ; extra == "docs"
Requires-Dist: sphinx ; extra == "docs"
Requires-Dist: sphinx-click ; extra == "docs"
Requires-Dist: pallets-sphinx-themes ; extra == "docs"
Project-URL: Home, https://github.com/rstms/bcc
Provides-Extra: dev
Provides-Extra: docs
